Workbook

Sheet Instructions
A1: RNK Civil — Excel master workbook (all phases) PHASE 1 — Master data: Setup_OTRules, Projects, Sites, Workers PHASE 2 — Attendance: daily rows in Attendance (link WorkerID, ProjectCode, SiteCode) PHASE 3 — Expenses: project costs, GST, approvals PHASE 4 — Payroll: set period in Period_Control; review AttendanceSummary; create PayrollRuns + PayrollLines PHASE 5 — Billing: Invoices + InvoiceLines (GST columns — confirm with your CA) PHASE 6 — Dashboard: KPIs (uses Period_Control dates for MTD-style filters) RULES • Use Excel Tables only (do not delete header row). Add new rows inside the table. • WorkerID / ProjectCode / SiteCode / InvoiceNo must stay unique and consistent. • OneDrive/SharePoint: turn on version history; take monthly backup copies. • This file is NOT a substitute for statutory payroll software — validate PF/ESI/PT/TDS with your CA. OT & PAY (simplified) • AttendanceSummary estimates pay using Period_Control dates. Monthly workers: EstBasePay uses gross/26 × paid working days cap (adjust policy in column note). • Refine OT and statutory columns before real payroll runs.

Sheet Period_Control
A1: PeriodLabel | B1: Apr-2026
A2: PeriodStart | B2: 46113
A3: PeriodEnd | B3: 46142
A4: Notes | B4: Change B2:B3 to filter AttendanceSummary & Dashboard period totals.

Sheet Setup_OTRules
A1: OTRuleID | B1: RuleName | C1: Multiplier | D1: MaxOTHrsPerDay | E1: Notes
A2: OT-STD | B2: Standard double rate | C2: 2 | D2: 4 | E2: Hours beyond 8 × (DailyRate/8)×Multiplier — refine in payroll

Sheet Projects
A1: ProjectCode | B1: ProjectName | C1: ClientName | D1: StartDate | E1: EndDate | F1: Status | G1: Budget | H1: Description
A2: PRJ-001 | B2: NH Road Package A | C2: NHAI | D2: 46023 | E2: 46387 | F2: Active | G2: 5000000 | H2: Example active project
A3: PRJ-002 | B3: Urban Drainage | C3: Municipal Corp | D3: 46082 | F3: Planning | G3: 1200000 | H3: Second project

Sheet Sites
A1: SiteCode | B1: ProjectCode | C1: SiteName | D1: Location | E1: Active
A2: S-001 | B2: PRJ-001 | C2: Km 12–15 Site Office | D2: NH-44 near km 12 | E2: Yes
A3: S-002 | B3: PRJ-001 | C3: Batch Plant | D3: Off-site batching | E3: Yes

Sheet Workers
A1: WorkerID | B1: FullName | C1: Phone | D1: PayType | E1: DailyRate | F1: MonthlyGross | G1: OTRuleID | H1: RateEffectiveDate | I1: Skill | J1: IndiaState | K1: PAN | L1: Active | M1: PrimaryProjectCode
A2: W-001 | B2: Ramesh Kumar | C2: 9876500001 | D2: Daily | E2: 800 | G2: OT-STD | H2: 46113 | I2: Mason | J2: Maharashtra | L2: Yes | M2: PRJ-001
A3: W-002 | B3: Suresh Patil | C3: 9876500002 | D3: Monthly | F3: 22000 | G3: OT-STD | H3: 46113 | I3: Supervisor | J3: Maharashtra | K3: ABCDE1234F | L3: Yes | M3: PRJ-001
A4: W-003 | B4: Vendor Labour A | D4: Daily | E4: 700 | G4: OT-STD | H4: 46113 | I4: Helper | J4: Maharashtra | L4: Yes | M4: PRJ-002

Sheet Attendance
A1: Date | B1: WorkerID | C1: ProjectCode | D1: SiteCode | E1: Status | F1: NormalHrs | G1: OTHrs | H1: Notes
A2: 46113 | B2: W-001 | C2: PRJ-001 | D2: S-001 | E2: Present | F2: 8 | G2: 2
A3: 46113 | B3: W-002 | C3: PRJ-001 | D3: S-001 | E3: Present | F3: 8 | G3: 0
A4: 46114 | B4: W-001 | C4: PRJ-001 | D4: S-001 | E4: Present | F4: 8 | G4: 0 | H4: Full day
A5: 46114 | B5: W-002 | C5: PRJ-001 | D5: S-001 | E5: Absent | F5: 0 | G5: 0 | H5: Leave

Sheet Expenses
A1: ExpenseDate | B1: ProjectCode | C1: Category | D1: Amount | E1: GSTAmount | F1: Vendor | G1: Approved | H1: BillLinkOrRef | I1: Notes
A2: 46115 | B2: PRJ-001 | C2: Petty cash | D2: 3500 | E2: 0 | F2: Local vendor | G2: Yes | H2: INV/PC/12 | I2: Site consumables
A3: 46116 | B3: PRJ-001 | C3: Fuel | D3: 8200 | E3: 1476 | F3: HP Petrol | G3: No | I3: Awaiting approval

Sheet AttendanceSummary
A1: WorkerID | B1: FullName | C1: PayType | D1: DailyRate | E1: MonthlyGross | F1: OTRuleID | G1: PaidDays | H1: TotalNormalHrs | I1: TotalOTHrs | J1: Multiplier | K1: EstOTPay | L1: EstBasePay | M1: EstGrossBeforeStatutory | N1: Notes
A2: W-001 | B2: =IFERROR(XLOOKUP([@[WorkerID]],tbl_Workers[WorkerID],tbl_Workers[FullName]),"") | C2: =IFERROR(XLOOKUP([@[WorkerID]],tbl_Workers[WorkerID],tbl_Workers[PayType]),"") | D2: =IFERROR(XLOOKUP([@[WorkerID]],tbl_Workers[WorkerID],tbl_Workers[DailyRate]),0) | E2: =IFERROR(XLOOKUP([@[WorkerID]],tbl_Workers[WorkerID],tbl_Workers[MonthlyGross]),0) | F2: =IFERROR(XLOOKUP([@[WorkerID]],tbl_Workers[WorkerID],tbl_Workers[OTRuleID]),"") | G2: =COUNTIFS(tbl_Attendance[WorkerID],[@[WorkerID]],tbl_Attendance[Date],">="&Period_Control!$B$2,tbl_Attendance[Date],"<="&Period_Control!$B$3,tbl_Attendance[Status],"Present") | H2: =SUMIFS(tbl_Attendance[NormalHrs],tbl_Attendance[WorkerID],[@[WorkerID]],tbl_Attendance[Date],">="&Period_Control!$B$2,tbl_Attendance[Date],"<="&Period_Control!$B$3) | I2: =SUMIFS(tbl_Attendance[OTHrs],tbl_Attendance[WorkerID],[@[WorkerID]],tbl_Attendance[Date],">="&Period_Control!$B$2,tbl_Attendance[Date],"<="&Period_Control!$B$3) | J2: =IFERROR(XLOOKUP([@[OTRuleID]],tbl_OTRules[OTRuleID],tbl_OTRules[Multiplier]),0) | K2: =[@[TotalOTHrs]]*([@[DailyRate]]/8)*[@[Multiplier]] | L2: =IF([@[PayType]]="Daily",[@[PaidDays]]*[@[DailyRate]],IF([@[PayType]]="Monthly",[@[MonthlyGross]]/26*MIN([@[PaidDays]],26),0)) | M2: =[@[EstBasePay]]+[@[EstOTPay]] | N2: Review LOP/statutory before paying
A3: W-002 | B3: =IFERROR(XLOOKUP([@[WorkerID]],tbl_Workers[WorkerID],tbl_Workers[FullName]),"") | C3: =IFERROR(XLOOKUP([@[WorkerID]],tbl_Workers[WorkerID],tbl_Workers[PayType]),"") | D3: =IFERROR(XLOOKUP([@[WorkerID]],tbl_Workers[WorkerID],tbl_Workers[DailyRate]),0) | E3: =IFERROR(XLOOKUP([@[WorkerID]],tbl_Workers[WorkerID],tbl_Workers[MonthlyGross]),0) | F3: =IFERROR(XLOOKUP([@[WorkerID]],tbl_Workers[WorkerID],tbl_Workers[OTRuleID]),"") | G3: =COUNTIFS(tbl_Attendance[WorkerID],[@[WorkerID]],tbl_Attendance[Date],">="&Period_Control!$B$2,tbl_Attendance[Date],"<="&Period_Control!$B$3,tbl_Attendance[Status],"Present") | H3: =SUMIFS(tbl_Attendance[NormalHrs],tbl_Attendance[WorkerID],[@[WorkerID]],tbl_Attendance[Date],">="&Period_Control!$B$2,tbl_Attendance[Date],"<="&Period_Control!$B$3) | I3: =SUMIFS(tbl_Attendance[OTHrs],tbl_Attendance[WorkerID],[@[WorkerID]],tbl_Attendance[Date],">="&Period_Control!$B$2,tbl_Attendance[Date],"<="&Period_Control!$B$3) | J3: =IFERROR(XLOOKUP([@[OTRuleID]],tbl_OTRules[OTRuleID],tbl_OTRules[Multiplier]),0) | K3: =[@[TotalOTHrs]]*([@[DailyRate]]/8)*[@[Multiplier]] | L3: =IF([@[PayType]]="Daily",[@[PaidDays]]*[@[DailyRate]],IF([@[PayType]]="Monthly",[@[MonthlyGross]]/26*MIN([@[PaidDays]],26),0)) | M3: =[@[EstBasePay]]+[@[EstOTPay]] | N3: Review LOP/statutory before paying
A4: W-003 | B4: =IFERROR(XLOOKUP([@[WorkerID]],tbl_Workers[WorkerID],tbl_Workers[FullName]),"") | C4: =IFERROR(XLOOKUP([@[WorkerID]],tbl_Workers[WorkerID],tbl_Workers[PayType]),"") | D4: =IFERROR(XLOOKUP([@[WorkerID]],tbl_Workers[WorkerID],tbl_Workers[DailyRate]),0) | E4: =IFERROR(XLOOKUP([@[WorkerID]],tbl_Workers[WorkerID],tbl_Workers[MonthlyGross]),0) | F4: =IFERROR(XLOOKUP([@[WorkerID]],tbl_Workers[WorkerID],tbl_Workers[OTRuleID]),"") | G4: =COUNTIFS(tbl_Attendance[WorkerID],[@[WorkerID]],tbl_Attendance[Date],">="&Period_Control!$B$2,tbl_Attendance[Date],"<="&Period_Control!$B$3,tbl_Attendance[Status],"Present") | H4: =SUMIFS(tbl_Attendance[NormalHrs],tbl_Attendance[WorkerID],[@[WorkerID]],tbl_Attendance[Date],">="&Period_Control!$B$2,tbl_Attendance[Date],"<="&Period_Control!$B$3) | I4: =SUMIFS(tbl_Attendance[OTHrs],tbl_Attendance[WorkerID],[@[WorkerID]],tbl_Attendance[Date],">="&Period_Control!$B$2,tbl_Attendance[Date],"<="&Period_Control!$B$3) | J4: =IFERROR(XLOOKUP([@[OTRuleID]],tbl_OTRules[OTRuleID],tbl_OTRules[Multiplier]),0) | K4: =[@[TotalOTHrs]]*([@[DailyRate]]/8)*[@[Multiplier]] | L4: =IF([@[PayType]]="Daily",[@[PaidDays]]*[@[DailyRate]],IF([@[PayType]]="Monthly",[@[MonthlyGross]]/26*MIN([@[PaidDays]],26),0)) | M4: =[@[EstBasePay]]+[@[EstOTPay]] | N4: Review LOP/statutory before paying

Sheet PayrollRuns
A1: RunID | B1: PeriodLabel | C1: PeriodStart | D1: PeriodEnd | E1: Status | F1: ApprovedBy | G1: ApprovedDate | H1: Notes
A2: RUN-202604 | B2: Apr-2026 | C2: 46113 | D2: 46142 | E2: Draft | H2: Lock after CA review

Sheet PayrollLines
A1: RunID | B1: WorkerID | C1: Component | D1: Amount | E1: StatutoryTag | F1: Notes
A2: RUN-202604 | B2: W-001 | C2: Gross_Est | D2: 0 | E2: Earning | F2: =EstGross from AttendanceSummary
A3: RUN-202604 | B3: W-001 | C3: PF_Employee | D3: 0 | E3: Deduction | F3: Enter per CA
A4: RUN-202604 | B4: W-002 | C4: Gross_Est | D4: 0 | E4: Earning

Sheet Invoices
A1: InvoiceNo | B1: InvoiceDate | C1: ProjectCode | D1: ClientName | E1: ClientGSTIN | F1: SubTotal | G1: CGST | H1: SGST | I1: IGST | J1: Total | K1: RetentionPct | L1: Status | M1: Notes
A2: INV-2026-001 | B2: 46117 | C2: PRJ-001 | D2: NHAI | E2: 27AAAAA0000A1Z5 | F2: 100000 | G2: 9000 | H2: 9000 | I2: 0 | J2: 118000 | K2: 10 | L2: Sent | M2: Example GST split — verify with CA

Sheet InvoiceLines
A1: InvoiceNo | B1: LineNo | C1: Description | D1: HSN_SAC | E1: TaxableAmount | F1: GST_Rate_Pct | G1: Notes
A2: INV-2026-001 | B2: 1 | C2: Mobilization & site establishment | D2: 9954 | E2: 100000 | F2: 18

Sheet Dashboard
A1: RNK Civil — KPIs (Phase 6)
A3: Active projects | B3: =COUNTIFS(tbl_Projects[Status],"Active")
A4: Total projects | B4: =COUNTA(tbl_Projects[ProjectCode])
A5: Active workers (Yes) | B5: =COUNTIFS(tbl_Workers[Active],"Yes")
A6: Period expenses (Approved=Yes) | B6: =SUMIFS(tbl_Expenses[Amount],tbl_Expenses[ExpenseDate],">="&Period_Control!$B$2,tbl_Expenses[ExpenseDate],"<="&Period_Control!$B$3,tbl_Expenses[Approved],"Yes")
A7: Period expense rows (all) | B7: =SUMIFS(tbl_Expenses[Amount],tbl_Expenses[ExpenseDate],">="&Period_Control!$B$2,tbl_Expenses[ExpenseDate],"<="&Period_Control!$B$3)
A8: Attendance Present days (all workers, period) | B8: =COUNTIFS(tbl_Attendance[Date],">="&Period_Control!$B$2,tbl_Attendance[Date],"<="&Period_Control!$B$3,tbl_Attendance[Status],"Present")
A9: Sum Est Gross (AttendanceSummary) | B9: =SUM(tbl_AttendanceSummary[EstGrossBeforeStatutory])
